geekbench_browser/__init__.py
geekbench_browser/__main__.py
geekbench_browser/_main.py
geekbench_browser/_option_eat_all.py
geekbench_browser/_rich_table.py
geekbench_browser/py.typed
geekbench_browser_python-0.1.10.dist-info/LICENSE
geekbench_browser_python-0.1.10.dist-info/METADATA
geekbench_browser_python-0.1.10.dist-info/WHEEL
geekbench_browser_python-0.1.10.dist-info/entry_points.txt
geekbench_browser_python-0.1.10.dist-info/RECORD
