Metadata-Version: 2.1
Name: geekbench-browser-python
Version: 0.1.10
Summary: Simple package for getting data from browser.geekbench.com
Home-page: https://github.com/34j/geekbench-browser-python
License: MIT
Author: 34j
Author-email: 34j.95a2p@simplelogin.com
Requires-Python: >=3.8,<4.0
Classifier: Development Status :: 2 - Pre-Alpha
Classifier: Intended Audience :: Developers
Classifier: License :: OSI Approved :: MIT License
Classifier: Natural Language :: English
Classifier: Operating System :: OS Independent
Classifier: Programming Language :: Python :: 3
Classifier: Programming Language :: Python :: 3.8
Classifier: Programming Language :: Python :: 3.9
Classifier: Programming Language :: Python :: 3.10
Classifier: Programming Language :: Python :: 3.11
Classifier: Programming Language :: Python :: 3.12
Classifier: Programming Language :: Python :: 3.13
Classifier: Topic :: Software Development :: Libraries
Requires-Dist: click
Requires-Dist: pandas (>=1.3)
Requires-Dist: py-cpuinfo (>=9.0.0,<10.0.0)
Requires-Dist: requests-cache
Requires-Dist: rich (>=13.3.1,<14.0.0)
Project-URL: Bug Tracker, https://github.com/34j/geekbench-browser-python/issues
Project-URL: Changelog, https://github.com/34j/geekbench-browser-python/blob/main/CHANGELOG.md
Project-URL: Documentation, https://geekbench-browser-python.readthedocs.io
Project-URL: Repository, https://github.com/34j/geekbench-browser-python
